JavaKaiyuanXiangmuZhongwenWendang20160518/README.md
JavaKaiyuanXiangmuZhongwenWendang20160518/__init__.py
JavaKaiyuanXiangmuZhongwenWendang20160518/__main__.py
JavaKaiyuanXiangmuZhongwenWendang20160518/file.epub
JavaKaiyuanXiangmuZhongwenWendang20160518/index.html
JavaKaiyuanXiangmuZhongwenWendang20160518/css/__init__.py
JavaKaiyuanXiangmuZhongwenWendang20160518/css/annotations.css
JavaKaiyuanXiangmuZhongwenWendang20160518/css/main.css
JavaKaiyuanXiangmuZhongwenWendang20160518/css/normalize.css
JavaKaiyuanXiangmuZhongwenWendang20160518/css/popup.css
JavaKaiyuanXiangmuZhongwenWendang20160518/font/__init__.py
JavaKaiyuanXiangmuZhongwenWendang20160518/font/fontello.eot
JavaKaiyuanXiangmuZhongwenWendang20160518/font/fontello.svg
JavaKaiyuanXiangmuZhongwenWendang20160518/font/fontello.ttf
JavaKaiyuanXiangmuZhongwenWendang20160518/font/fontello.woff
JavaKaiyuanXiangmuZhongwenWendang20160518/img/__init__.py
JavaKaiyuanXiangmuZhongwenWendang20160518/img/annotator-glyph-sprite.png
JavaKaiyuanXiangmuZhongwenWendang20160518/img/annotator-icon-sprite.png
JavaKaiyuanXiangmuZhongwenWendang20160518/img/apple-touch-icon.png
JavaKaiyuanXiangmuZhongwenWendang20160518/img/cancelfullscreen.png
JavaKaiyuanXiangmuZhongwenWendang20160518/img/close.png
JavaKaiyuanXiangmuZhongwenWendang20160518/img/fullscreen.png
JavaKaiyuanXiangmuZhongwenWendang20160518/img/loader.gif
JavaKaiyuanXiangmuZhongwenWendang20160518/img/menu-icon.png
JavaKaiyuanXiangmuZhongwenWendang20160518/img/save.png
JavaKaiyuanXiangmuZhongwenWendang20160518/img/saved.png
JavaKaiyuanXiangmuZhongwenWendang20160518/img/settings-s.png
JavaKaiyuanXiangmuZhongwenWendang20160518/img/settings.png
JavaKaiyuanXiangmuZhongwenWendang20160518/img/star.png
JavaKaiyuanXiangmuZhongwenWendang20160518/js/__init__.py
JavaKaiyuanXiangmuZhongwenWendang20160518/js/epub.js
JavaKaiyuanXiangmuZhongwenWendang20160518/js/epub.min.js
JavaKaiyuanXiangmuZhongwenWendang20160518/js/epub.min.map
JavaKaiyuanXiangmuZhongwenWendang20160518/js/hooks.min.js
java_kaiyuan_xiangmu_zhongwen_wendang_20160518-2024.3.1.0.dist-info/METADATA
java_kaiyuan_xiangmu_zhongwen_wendang_20160518-2024.3.1.0.dist-info/WHEEL
java_kaiyuan_xiangmu_zhongwen_wendang_20160518-2024.3.1.0.dist-info/entry_points.txt
java_kaiyuan_xiangmu_zhongwen_wendang_20160518-2024.3.1.0.dist-info/top_level.txt
java_kaiyuan_xiangmu_zhongwen_wendang_20160518-2024.3.1.0.dist-info/RECORD
